hwp_hwpx_editor/__init__.py
hwp_hwpx_editor/document.py
hwp_hwpx_editor/parser.py
hwp_hwpx_editor/simple.py
hwp_hwpx_editor/core/__init__.py
hwp_hwpx_editor/core/exceptions.py
hwp_hwpx_editor/core/jvm.py
hwp_hwpx_editor/hwp/__init__.py
hwp_hwpx_editor/hwp/comment.py
hwp_hwpx_editor/hwp/control.py
hwp_hwpx_editor/hwp/creator.py
hwp_hwpx_editor/hwp/extractor.py
hwp_hwpx_editor/hwp/field.py
hwp_hwpx_editor/hwp/hyperlink.py
hwp_hwpx_editor/hwp/image.py
hwp_hwpx_editor/hwp/reader.py
hwp_hwpx_editor/hwp/table.py
hwp_hwpx_editor/hwp/writer.py
hwp_hwpx_editor/hwpx/__init__.py
hwp_hwpx_editor/hwpx/comment.py
hwp_hwpx_editor/hwpx/creator.py
hwp_hwpx_editor/hwpx/extractor.py
hwp_hwpx_editor/hwpx/finder.py
hwp_hwpx_editor/hwpx/reader.py
hwp_hwpx_editor/hwpx/table.py
hwp_hwpx_editor/hwpx/text.py
hwp_hwpx_editor/hwpx/writer.py
hwp_hwpx_editor/jars/hwplib-1.1.10.jar
hwp_hwpx_editor/jars/hwpxlib-1.0.8.jar
hwp_hwpx_editor/jars/poi-3.9.jar
hwp_hwpx_editor/jars/poi-ooxml-3.9.jar
hwp_hwpx_editor/jars/poi-scratchpad-3.9.jar
hwp_hwpx_editor-0.1.4.dist-info/licenses/LICENSE
hwp_hwpx_editor-0.1.4.dist-info/METADATA
hwp_hwpx_editor-0.1.4.dist-info/WHEEL
hwp_hwpx_editor-0.1.4.dist-info/top_level.txt
hwp_hwpx_editor-0.1.4.dist-info/RECORD
