Metadata-Version: 2.4
Name: hwp-hwpx-editor
Version: 0.1.4
Summary: JVM 기반 HWP/HWPX 문서 편집 라이브러리 (hwp-hwpx-parser 확장)
Author-email: Daehyeon Kim <qwertypotter@gachon.ac.kr>
License-Expression: Apache-2.0
Project-URL: Homepage, https://github.com/KimDaehyeon6873/hwp-hwpx-editor
Project-URL: Repository, https://github.com/KimDaehyeon6873/hwp-hwpx-editor.git
Project-URL: Bug Tracker, https://github.com/KimDaehyeon6873/hwp-hwpx-editor/issues
Keywords: hwp,hwpx,korean,word-processor,editor,jvm
Classifier: Development Status :: 3 - Alpha
Classifier: Intended Audience :: Developers
Classifier: Operating System :: OS Independent
Classifier: Programming Language :: Python :: 3
Classifier: Programming Language :: Python :: 3.8
Classifier: Programming Language :: Python :: 3.9
Classifier: Programming Language :: Python :: 3.10
Classifier: Programming Language :: Python :: 3.11
Classifier: Programming Language :: Python :: 3.12
Classifier: Programming Language :: Python :: 3.13
Classifier: Programming Language :: Python :: 3.14
Classifier: Topic :: Text Processing :: Markup
Requires-Python: >=3.8
License-File: LICENSE
Requires-Dist: hwp-hwpx-parser>=0.1.0
Requires-Dist: JPype1>=1.4.0
Provides-Extra: dev
Requires-Dist: pytest>=7.0; extra == "dev"
Requires-Dist: pytest-cov>=4.0; extra == "dev"
Requires-Dist: black>=22.0; extra == "dev"
Requires-Dist: mypy>=1.0; extra == "dev"
Dynamic: license-file
